{
  "token_address": "EEWrikw2vKeXMHfVBbnDeH54to2LdnxR7GJAciSKpump",
  "token_info": {
    "onChainMetadata": {
      "metadata": {
        "name": "Bullcoin",
        "symbol": "$BULL"
      }
    },
    "legacyMetadata": {
      "description": "Every Bull is Our Movement to Shine. $BULL",
      "name": "Bullcoin",
      "symbol": "$BULL"
    },
    "market_cap_usd": 323537.13
  },
  "market_cap_usd": 301667.0,
  "first_transaction_time": "2025-11-17T14:06:26",
  "analysis_window_end": "2139-12-17T05:06:26",
  "early_bidders": [
    {
      "wallet_address": "2ufzqteFAk4osq9P33E37RJD3H2ZaT4tTrDZJwCjqWYX",
      "first_buy_time": "2025-11-17T14:06:26",
      "total_usd": 17216.1178532,
      "transaction_count": 1,
      "average_buy_usd": 17216.1178532,
      "wallet_balance_usd": 6746.947589090621
    },
    {
      "wallet_address": "HyXoX6QFfwBYxYePN12h3oKWrBVhMuZoU6iLVuDkEpj3",
      "first_buy_time": "2025-11-17T14:06:27",
      "total_usd": 17001.0718114,
      "transaction_count": 1,
      "average_buy_usd": 17001.0718114,
      "wallet_balance_usd": 0.25424511120000004
    },
    {
      "wallet_address": "2d8fcdN3GtmwGkvnHzXXHJrQQSdXeVvAYGPaYfEi3bsX",
      "first_buy_time": "2025-11-17T14:06:27",
      "total_usd": 122.34815160000001,
      "transaction_count": 1,
      "average_buy_usd": 122.34815160000001,
      "wallet_balance_usd": 1529.23452316998
    },
    {
      "wallet_address": "8EqHEwomuwrQ5yTeugUDzrLStR8dHxaQifo3pbj8En32",
      "first_buy_time": "2025-11-17T14:06:28",
      "total_usd": 61.145858,
      "transaction_count": 1,
      "average_buy_usd": 61.145858,
      "wallet_balance_usd": 9736.44522083496
    },
    {
      "wallet_address": "4QrC8PY3V5NfpPdggJoPuJp1M2731ruQxfEUzukrKVH4",
      "first_buy_time": "2025-11-17T14:06:29",
      "total_usd": 79.2659874,
      "transaction_count": 1,
      "average_buy_usd": 79.2659874,
      "wallet_balance_usd": 2131.21036946248
    },
    {
      "wallet_address": "BMJn9TcEn9SRGeFfqGBYkcH5BXBef1zpnDtMHEycEo8L",
      "first_buy_time": "2025-11-17T14:06:29",
      "total_usd": 618.0284,
      "transaction_count": 1,
      "average_buy_usd": 618.0284,
      "wallet_balance_usd": 9956.52359771245
    },
    {
      "wallet_address": "ESXWLJEKgMneXkNGoewmNeJ87r3eqsvNwkF8M7stJ6RT",
      "first_buy_time": "2025-11-17T14:06:29",
      "total_usd": 61.2544468,
      "transaction_count": 1,
      "average_buy_usd": 61.2544468,
      "wallet_balance_usd": 2.7090124022000004
    },
    {
      "wallet_address": "GXjJNbBmCCRgNHB3xqBG1q397iMoVXwAudfhETVXNqf1",
      "first_buy_time": "2025-11-17T14:06:31",
      "total_usd": 12698.511159399999,
      "transaction_count": 10,
      "average_buy_usd": 1269.85111594,
      "wallet_balance_usd": 26682.396237284855
    },
    {
      "wallet_address": "9ECZk7bzeiQYSeGhcgtfUDRRvAf5QHiFoj4nGP5v4icK",
      "first_buy_time": "2025-11-17T14:06:31",
      "total_usd": 71.3411738,
      "transaction_count": 1,
      "average_buy_usd": 71.3411738,
      "wallet_balance_usd": 89.14896619342001
    },
    {
      "wallet_address": "HghNwMYZKDtBkEgisEAABgo8e5gn83gcn1gdndmTVxXR",
      "first_buy_time": "2025-11-17T14:06:31",
      "total_usd": 55.908075999999994,
      "transaction_count": 1,
      "average_buy_usd": 55.908075999999994,
      "wallet_balance_usd": 149.13583522299
    },
    {
      "wallet_address": "G71SzGVpG5DeqtEufWUthFp9cFE171CsjnhCoTSKqosF",
      "first_buy_time": "2025-11-17T14:06:31",
      "total_usd": 56.2297898,
      "transaction_count": 1,
      "average_buy_usd": 56.2297898,
      "wallet_balance_usd": 118.1954012355
    },
    {
      "wallet_address": "9q3yazmm4pacWG7sHDb7TLbB2dPiHYqLCt7YGUXWPHAt",
      "first_buy_time": "2025-11-17T14:06:31",
      "total_usd": 199.364,
      "transaction_count": 1,
      "average_buy_usd": 199.364,
      "wallet_balance_usd": 16084.46433061969
    },
    {
      "wallet_address": "13acKoAFf1cM34QiEDEqybwv9L5mam5HTz8XFSJu4xqB",
      "first_buy_time": "2025-11-17T14:06:31",
      "total_usd": 50.077816799999994,
      "transaction_count": 1,
      "average_buy_usd": 50.077816799999994,
      "wallet_balance_usd": 1775.7435782345
    },
    {
      "wallet_address": "8mNw7FBnUZmUeX3mioGytaGQ8YRrbPE7PCS1z6WyusLs",
      "first_buy_time": "2025-11-17T14:06:45",
      "total_usd": 101.6465234,
      "transaction_count": 1,
      "average_buy_usd": 101.6465234,
      "wallet_balance_usd": 1480.60513653304
    },
    {
      "wallet_address": "FNEjVzvsrJEVZ6eJ4oDu9UtGbT3bMKzTe6s9YWCch1yN",
      "first_buy_time": "2025-11-17T14:06:55",
      "total_usd": 148.816816,
      "transaction_count": 2,
      "average_buy_usd": 74.408408,
      "wallet_balance_usd": 49.86958898409
    },
    {
      "wallet_address": "HQ56cGPm8KHqeUp1PT6PSRSDMqYy9xuVdNye3QqfMnf1",
      "first_buy_time": "2025-11-17T14:07:15",
      "total_usd": 203.29085619999998,
      "transaction_count": 1,
      "average_buy_usd": 203.29085619999998,
      "wallet_balance_usd": 756.6650239151201
    },
    {
      "wallet_address": "5aXbFCpg5f142baZfGgkRs7s75h7yuSrq4Mw4NtD8c91",
      "first_buy_time": "2025-11-17T14:07:42",
      "total_usd": 103.05489139999999,
      "transaction_count": 1,
      "average_buy_usd": 103.05489139999999,
      "wallet_balance_usd": 1109.28405347037
    },
    {
      "wallet_address": "23RP9UTyu6h3jhHhEjV8midsojjqT5VSKCo5mMCw1kVZ",
      "first_buy_time": "2025-11-17T14:08:12",
      "total_usd": 103.616816,
      "transaction_count": 2,
      "average_buy_usd": 51.808408,
      "wallet_balance_usd": 166.03366887879
    },
    {
      "wallet_address": "GUM1LDV4acyWxXqEPnUg5CiBjv4xZ1LPDNwrjY1UAcFW",
      "first_buy_time": "2025-11-17T14:30:03",
      "total_usd": 60.6788168,
      "transaction_count": 1,
      "average_buy_usd": 60.6788168,
      "wallet_balance_usd": 3004.98494917806
    },
    {
      "wallet_address": "EAPMoMGkesj4wyAJ5wBRwtmnAA6nkU8s6WWB5Jhnb1UT",
      "first_buy_time": "2025-11-17T14:36:14",
      "total_usd": 70.281,
      "transaction_count": 1,
      "average_buy_usd": 70.281,
      "wallet_balance_usd": 670.89705826729
    },
    {
      "wallet_address": "JB6tyYq6ScYUAb6NiM2W36A6DwZuhw2yBM7RXzk16PKf",
      "first_buy_time": "2025-11-17T14:37:57",
      "total_usd": 100.445816,
      "transaction_count": 1,
      "average_buy_usd": 100.445816,
      "wallet_balance_usd": 728.22612881881
    },
    {
      "wallet_address": "7x2rQoyKPxERtQbPRZk9cJu6rE3dyqn3o9ii9RaCepKe",
      "first_buy_time": "2025-11-17T14:38:35",
      "total_usd": 64.50100020000001,
      "transaction_count": 1,
      "average_buy_usd": 64.50100020000001,
      "wallet_balance_usd": 9.873738985500001
    },
    {
      "wallet_address": "EWFBnY2UgTyytoahY8nM4SGkbai2hwae7U4QQsvTmEnb",
      "first_buy_time": "2025-11-17T14:39:12",
      "total_usd": 100.2559998,
      "transaction_count": 1,
      "average_buy_usd": 100.2559998,
      "wallet_balance_usd": 45.073634867790005
    },
    {
      "wallet_address": "4JwM7hQYhSofMEh96V9aCFUHvSFkCfGt6YNzoU9zjiCT",
      "first_buy_time": "2025-11-17T14:39:58",
      "total_usd": 52.015816,
      "transaction_count": 1,
      "average_buy_usd": 52.015816,
      "wallet_balance_usd": 71.5848829252
    },
    {
      "wallet_address": "GvWZYBGUoSCFhMhdossTn989FfQb5wpCKvvm6f4ucvYa",
      "first_buy_time": "2025-11-17T14:41:53",
      "total_usd": 64.581,
      "transaction_count": 1,
      "average_buy_usd": 64.581,
      "wallet_balance_usd": 168.57677529544
    },
    {
      "wallet_address": "4Fda8AAuVj1NYuLLs6z3gRYUMeiyGHWgYCqmb28P3g1W",
      "first_buy_time": "2025-11-17T14:42:42",
      "total_usd": 100.0310002,
      "transaction_count": 1,
      "average_buy_usd": 100.0310002,
      "wallet_balance_usd": 37.98650381806
    },
    {
      "wallet_address": "8EZ69r8amYfk3UKPyqWEiRrJbzeSzLCKR475nKfV3Huq",
      "first_buy_time": "2025-11-17T14:44:12",
      "total_usd": 100.0310002,
      "transaction_count": 1,
      "average_buy_usd": 100.0310002,
      "wallet_balance_usd": 65.4447071593
    },
    {
      "wallet_address": "E7PbQh8ZMt6d2VVUP4rAp8hBdo2Pr49nn8WR16DnTheT",
      "first_buy_time": "2025-11-17T14:45:40",
      "total_usd": 70.4122162,
      "transaction_count": 1,
      "average_buy_usd": 70.4122162,
      "wallet_balance_usd": 5.724570035030001
    },
    {
      "wallet_address": "CiY7Me6SQaUiMM6hawFVZu93ZHd1PPGyKUsyNrt91yhv",
      "first_buy_time": "2025-11-17T14:46:13",
      "total_usd": 70.4458162,
      "transaction_count": 1,
      "average_buy_usd": 70.4458162,
      "wallet_balance_usd": 22.74653030617
    },
    {
      "wallet_address": "5kNkgTBAnvXEzSSc1muuNRfgKtttZdSUVDMaAXCnXA6x",
      "first_buy_time": "2025-11-17T14:49:36",
      "total_usd": 1486.6331963999999,
      "transaction_count": 3,
      "average_buy_usd": 495.54439879999995,
      "wallet_balance_usd": 296.37294558222
    },
    {
      "wallet_address": "GykNYC5ThitAxUQFGY1rjG9cdKfGCoHtaUaQtEt21y7z",
      "first_buy_time": "2025-11-17T14:51:57",
      "total_usd": 74.9059998,
      "transaction_count": 1,
      "average_buy_usd": 74.9059998,
      "wallet_balance_usd": 2.7333097369500003
    },
    {
      "wallet_address": "FZhFhENLyL5NbyFXP9qNfMMfCPo6zYhu26JyhtR5CWG4",
      "first_buy_time": "2025-11-17T14:54:25",
      "total_usd": 50.501795,
      "transaction_count": 1,
      "average_buy_usd": 50.501795,
      "wallet_balance_usd": 19.266414834069998
    },
    {
      "wallet_address": "6fJ1GdT2fHCpuLnea3UQWyQBtEXqbXtXsUTsvhJ6pZHZ",
      "first_buy_time": "2025-11-17T14:54:56",
      "total_usd": 50.516504,
      "transaction_count": 1,
      "average_buy_usd": 50.516504,
      "wallet_balance_usd": 73.04013845200001
    },
    {
      "wallet_address": "Ey1g81jL4Y8ZpgYVaQwYzRZHQhgAutjoAoYemgtKaTcL",
      "first_buy_time": "2025-11-17T14:54:56",
      "total_usd": 50.8809112,
      "transaction_count": 1,
      "average_buy_usd": 50.8809112,
      "wallet_balance_usd": 296.68283751458
    },
    {
      "wallet_address": "49nFDVumssYRtbM1RLfuQKJ9C8eyzr496T9nkADP4wX7",
      "first_buy_time": "2025-11-17T14:54:56",
      "total_usd": 53.33145700000001,
      "transaction_count": 1,
      "average_buy_usd": 53.33145700000001,
      "wallet_balance_usd": 382.23201926334
    },
    {
      "wallet_address": "6ctPq2hmjWmb6vSVbqn4Q6gvGeMp4nHCZPf1AiCBcDHK",
      "first_buy_time": "2025-11-17T14:54:56",
      "total_usd": 51.6211622,
      "transaction_count": 1,
      "average_buy_usd": 51.6211622,
      "wallet_balance_usd": 149.86504304963003
    },
    {
      "wallet_address": "3KZyst865PstrTvSd6Xr6bKS4vAQ3hPuT6hY42oQLgQX",
      "first_buy_time": "2025-11-17T14:55:03",
      "total_usd": 122.056816,
      "transaction_count": 2,
      "average_buy_usd": 61.028408,
      "wallet_balance_usd": 1278.6682535198
    }
  ],
  "total_unique_buyers": 37,
  "total_transactions_analyzed": 250,
  "api_credits_used": 338
}